<?xml version="1.0" encoding="utf-8"?>
<!DOCTYPE hibernate-mapping PUBLIC "-//Hibernate/Hibernate Mapping DTD 3.0//EN"
"http://hibernate.sourceforge.net/hibernate-mapping-3.0.dtd">
<!-- 
    Mapping file autogenerated by MyEclipse Persistence Tools
-->
<hibernate-mapping>
    <class name="com.wtc.hcis.da.EntityAcctMap" table="entity_acct_map" catalog="hcisit">
        <composite-id name="id" class="com.wtc.hcis.da.EntityAcctMapId">
            <key-property name="entityId" type="java.lang.Integer">
                <column name="ENTITY_ID" />
            </key-property>
            <key-property name="entityType" type="java.lang.String">
                <column name="ENTITY_TYPE" length="25" />
            </key-property>
        </composite-id>
        <version name="version" type="java.lang.Integer">
            <column name="VERSION" not-null="true" />
        </version>
        <property name="businessPartnerId" type="java.lang.Integer">
            <column name="BUSINESS_PARTNER_ID" not-null="true" />
        </property>
        <property name="userId" type="java.lang.String">
            <column name="USER_ID" length="45" not-null="true" />
        </property>
        <property name="lastModifiedDtm" type="java.util.Date">
            <column name="LAST_MODIFIED_DTM" length="19" not-null="true" />
        </property>
    </class>
</hibernate-mapping>
